poaster/__about__.py
poaster/__init__.py
poaster/app.py
poaster/cli.py
poaster/dependencies.py
poaster/access/__init__.py
poaster/access/api.py
poaster/access/cli.py
poaster/access/components.py
poaster/access/repository.py
poaster/access/schemas.py
poaster/access/services.py
poaster/access/tables.py
poaster/access/web.py
poaster/bulletin/__init__.py
poaster/bulletin/api.py
poaster/bulletin/components.py
poaster/bulletin/repository.py
poaster/bulletin/schemas.py
poaster/bulletin/services.py
poaster/bulletin/tables.py
poaster/bulletin/web.py
poaster/core/__init__.py
poaster/core/components.py
poaster/core/config.py
poaster/core/exceptions.py
poaster/core/hashing.py
poaster/core/http_exceptions.py
poaster/core/oauth.py
poaster/core/schemas.py
poaster/core/sessions.py
poaster/core/tables.py
poaster/migrations/__init__.py
poaster/migrations/alembic.ini
poaster/migrations/env.py
poaster/migrations/script.py.mako
poaster/migrations/upgrade.py
poaster/migrations/versions/0b3ee652b174_.py
poaster/migrations/versions/34b9b6b1c9a3_.py
poaster/migrations/versions/821b409e627c_.py
poaster/static/app.css
poaster/static/concrete.css
poaster/static/normalize.css
poaster-1.5.0.dist-info/METADATA
poaster-1.5.0.dist-info/WHEEL
poaster-1.5.0.dist-info/entry_points.txt
poaster-1.5.0.dist-info/licenses/LICENSE
poaster-1.5.0.dist-info/RECORD
