Metadata-Version: 2.3
Name: poaster
Version: 1.5.0
Summary: Minimal, libre bulletin board for posts.
Project-URL: Homepage, https://sr.ht/~loges/poaster
Project-URL: Source, https://git.sr.ht/~loges/poaster
Project-URL: Issues, https://todo.sr.ht/~loges/poaster
Author-email: Logan Connolly <me@loganconnolly.com>
License-Expression: AGPL-3.0-or-later
License-File: LICENSE
Classifier: Development Status :: 4 - Beta
Classifier: Programming Language :: Python
Classifier: Programming Language :: Python :: 3.9
Classifier: Programming Language :: Python :: 3.10
Classifier: Programming Language :: Python :: 3.11
Classifier: Programming Language :: Python :: 3.12
Classifier: Programming Language :: Python :: Implementation :: CPython
Classifier: Programming Language :: Python :: Implementation :: PyPy
Requires-Python: >=3.9
Requires-Dist: aiosqlite
Requires-Dist: alembic
Requires-Dist: click
Requires-Dist: fastapi
Requires-Dist: haitch>=0.9.0
Requires-Dist: mistletoe
Requires-Dist: passlib[argon2]
Requires-Dist: pydantic-settings
Requires-Dist: python-jose
Requires-Dist: python-multipart
Requires-Dist: sqlalchemy[asyncio,mypy]
Requires-Dist: uvicorn[standard]
